odoo9_addon_account_fiscal_year-9.0.1.0.0.99.dev21-py3.8-nspkg.pth
odoo_addons/account_fiscal_year/README.rst
odoo_addons/account_fiscal_year/__init__.py
odoo_addons/account_fiscal_year/__openerp__.py
odoo_addons/account_fiscal_year/data/date_range_type.xml
odoo_addons/account_fiscal_year/i18n/account_fiscal_year.pot
odoo_addons/account_fiscal_year/i18n/am.po
odoo_addons/account_fiscal_year/i18n/ar.po
odoo_addons/account_fiscal_year/i18n/ca.po
odoo_addons/account_fiscal_year/i18n/da.po
odoo_addons/account_fiscal_year/i18n/de.po
odoo_addons/account_fiscal_year/i18n/el_GR.po
odoo_addons/account_fiscal_year/i18n/es.po
odoo_addons/account_fiscal_year/i18n/es_ES.po
odoo_addons/account_fiscal_year/i18n/es_MX.po
odoo_addons/account_fiscal_year/i18n/eu.po
odoo_addons/account_fiscal_year/i18n/fi.po
odoo_addons/account_fiscal_year/i18n/fr.po
odoo_addons/account_fiscal_year/i18n/fr_CA.po
odoo_addons/account_fiscal_year/i18n/fr_FR.po
odoo_addons/account_fiscal_year/i18n/hr.po
odoo_addons/account_fiscal_year/i18n/hr_HR.po
odoo_addons/account_fiscal_year/i18n/it.po
odoo_addons/account_fiscal_year/i18n/nb.po
odoo_addons/account_fiscal_year/i18n/nb_NO.po
odoo_addons/account_fiscal_year/i18n/nl.po
odoo_addons/account_fiscal_year/i18n/nl_BE.po
odoo_addons/account_fiscal_year/i18n/nl_NL.po
odoo_addons/account_fiscal_year/i18n/pt.po
odoo_addons/account_fiscal_year/i18n/pt_BR.po
odoo_addons/account_fiscal_year/i18n/pt_PT.po
odoo_addons/account_fiscal_year/i18n/ro.po
odoo_addons/account_fiscal_year/i18n/sk.po
odoo_addons/account_fiscal_year/i18n/sl.po
odoo_addons/account_fiscal_year/i18n/tr.po
odoo_addons/account_fiscal_year/i18n/zh_CN.po
odoo_addons/account_fiscal_year/models/__init__.py
odoo_addons/account_fiscal_year/models/date_range_type.py
odoo_addons/account_fiscal_year/models/res_company.py
odoo_addons/account_fiscal_year/static/description/icon.png
odoo_addons/account_fiscal_year/tests/__init__.py
odoo_addons/account_fiscal_year/tests/test_account_fiscal_year.py
odoo9_addon_account_fiscal_year-9.0.1.0.0.99.dev21.dist-info/METADATA
odoo9_addon_account_fiscal_year-9.0.1.0.0.99.dev21.dist-info/WHEEL
odoo9_addon_account_fiscal_year-9.0.1.0.0.99.dev21.dist-info/namespace_packages.txt
odoo9_addon_account_fiscal_year-9.0.1.0.0.99.dev21.dist-info/top_level.txt
odoo9_addon_account_fiscal_year-9.0.1.0.0.99.dev21.dist-info/RECORD
